huaweicloudsdkec/__init__.py
huaweicloudsdkec/v1/__init__.py
huaweicloudsdkec/v1/ec_async_client.py
huaweicloudsdkec/v1/ec_client.py
huaweicloudsdkec/v1/model/__init__.py
huaweicloudsdkec/v1/model/access_point.py
huaweicloudsdkec/v1/model/add_ecn_with_er_request.py
huaweicloudsdkec/v1/model/add_ecn_with_er_response.py
huaweicloudsdkec/v1/model/add_ecn_with_ieg_request.py
huaweicloudsdkec/v1/model/add_ecn_with_ieg_response.py
huaweicloudsdkec/v1/model/add_ecn_with_vpc_request.py
huaweicloudsdkec/v1/model/add_ecn_with_vpc_request_body.py
huaweicloudsdkec/v1/model/add_ecn_with_vpc_response.py
huaweicloudsdkec/v1/model/add_vrrp_config_request.py
huaweicloudsdkec/v1/model/add_vrrp_config_response.py
huaweicloudsdkec/v1/model/change_ieg_password_request.py
huaweicloudsdkec/v1/model/change_ieg_password_response.py
huaweicloudsdkec/v1/model/change_password_body.py
huaweicloudsdkec/v1/model/create_access_point_request_body.py
huaweicloudsdkec/v1/model/create_ecn_access_point_request.py
huaweicloudsdkec/v1/model/create_ecn_access_point_response.py
huaweicloudsdkec/v1/model/create_equipment_lan_config_request.py
huaweicloudsdkec/v1/model/create_equipment_lan_config_response.py
huaweicloudsdkec/v1/model/create_equipment_request.py
huaweicloudsdkec/v1/model/create_equipment_response.py
huaweicloudsdkec/v1/model/create_equipment_static_route_config_request.py
huaweicloudsdkec/v1/model/create_equipment_static_route_config_response.py
huaweicloudsdkec/v1/model/create_update_vrrp_config_request_body.py
huaweicloudsdkec/v1/model/delete_ecn_access_point_request.py
huaweicloudsdkec/v1/model/delete_ecn_access_point_response.py
huaweicloudsdkec/v1/model/delete_ecn_with_er_request.py
huaweicloudsdkec/v1/model/delete_ecn_with_er_response.py
huaweicloudsdkec/v1/model/delete_ecn_with_ieg_request.py
huaweicloudsdkec/v1/model/delete_ecn_with_ieg_response.py
huaweicloudsdkec/v1/model/delete_ecn_with_vpc_request.py
huaweicloudsdkec/v1/model/delete_ecn_with_vpc_response.py
huaweicloudsdkec-3.1.184.dist-info/METADATA
huaweicloudsdkec-3.1.184.dist-info/WHEEL
huaweicloudsdkec-3.1.184.dist-info/licenses/LICENSE
huaweicloudsdkec-3.1.184.dist-info/RECORD
